tests/__init__.py
tests/conftest.py
tests/test_account.py
tests/test_ad_params.py
tests/test_album.py
tests/test_album_event.py
tests/test_alert.py
tests/test_alert_button.py
tests/test_artist.py
tests/test_artist_albums.py
tests/test_artist_event.py
tests/test_artist_tracks.py
tests/test_auto_renewable.py
tests/test_best.py
tests/test_block.py
tests/test_block_entity.py
tests/test_brand.py
tests/test_brief_info.py
tests/test_case_forms.py
tests/test_chart.py
tests/test_chart_info.py
tests/test_chart_info_menu.py
tests/test_chart_info_menu_item.py
tests/test_chart_item.py
tests/test_contest.py
tests/test_context.py
tests/test_convert_track_id.py
tests/test_counts.py
tests/test_cover.py
tests/test_custom_wave.py
tests/test_dashboard.py
tests/test_day.py
tests/test_deactivation.py
tests/test_deprecation.py
tests/test_description.py
tests/test_discrete_scale.py
tests/test_download_info.py
tests/test_enum.py
tests/test_event.py
tests/test_feed.py
tests/test_generated_playlist.py
tests/test_genre.py
tests/test_icon.py
tests/test_id.py
tests/test_images.py
tests/test_invocation_info.py
tests/test_label.py
tests/test_landing.py
tests/test_landing_list.py
tests/test_licence_text_part.py
tests/test_like.py
tests/test_link.py
tests/test_lyrics.py
tests/test_lyrics_info.py
tests/test_lyrics_major.py
tests/test_made_for.py
tests/test_major.py
tests/test_meta_data.py
tests/test_mix_link.py
tests/test_non_auto_renewable.py
tests/test_normalization.py
tests/test_open_graph_data.py
tests/test_operator.py
tests/test_pager.py
tests/test_passport_phone.py
tests/test_permission_alerts.py
tests/test_permissions.py
tests/test_personal_playlists_data.py
tests/test_play_context.py
tests/test_play_contexts_data.py
tests/test_play_counter.py
tests/test_playlist.py
tests/test_playlist_absence.py
tests/test_playlist_id.py
tests/test_playlist_recommendations.py
tests/test_plus.py
tests/test_poetry_lover_match.py
tests/test_price.py
tests/test_product.py
tests/test_promo_code_status.py
yandex_music_test-2.2.0.dist-info/LICENSE
yandex_music_test-2.2.0.dist-info/METADATA
yandex_music_test-2.2.0.dist-info/WHEEL
yandex_music_test-2.2.0.dist-info/top_level.txt
yandex_music_test-2.2.0.dist-info/RECORD
