Metadata-Version: 2.1
Name: yandex-music-test
Version: 2.2.0
Summary: клон репы неофициального апи яндекса для получения whl файла для установки в Pyodide
Home-page: https://github.com/MarshalX/yandex-music-api
Author: a2sh3r
Author-email: ashurmetovmm@gmail.com
License: LGPLv3
Project-URL: Documentation, https://yandex-music.rtfd.io
Project-URL: Changes, https://github.com/MarshalX/yandex-music-api/blob/main/CHANGES.md
Project-URL: Tracker, https://github.com/MarshalX/yandex-music-api/issues
Project-URL: Telegram chat, https://t.me/yandex_music_api
Project-URL: Codecov, https://codecov.io/gh/MarshalX/yandex-music-api
Project-URL: Codacy, https://app.codacy.com/gh/MarshalX/yandex-music-api
Keywords: python yandex music api wrapper library client питон пайтон яндекс музыка апи обёртка библиотека клиент
Classifier: Development Status :: 5 - Production/Stable
Classifier: Natural Language :: Russian
Classifier: Intended Audience :: Developers
Classifier: License :: OSI Approved :: GNU Lesser General Public License v3 (LGPLv3)
Classifier: Operating System :: OS Independent
Classifier: Topic :: Internet
Classifier: Topic :: Multimedia :: Sound/Audio
Classifier: Topic :: Software Development :: Libraries
Classifier: Topic :: Software Development :: Libraries :: Python Modules
Classifier: Topic :: Software Development :: Libraries :: Application Frameworks
Classifier: Programming Language :: Python
Classifier: Programming Language :: Python :: 3.7
Classifier: Programming Language :: Python :: 3.8
Classifier: Programming Language :: Python :: 3.9
Classifier: Programming Language :: Python :: 3.10
Classifier: Programming Language :: Python :: 3.11
Classifier: Programming Language :: Python :: 3.12
Classifier: Programming Language :: Python :: Implementation
Classifier: Programming Language :: Python :: Implementation :: CPython
Classifier: Programming Language :: Python :: Implementation :: PyPy
Requires-Python: ~=3.7
License-File: LICENSE
Requires-Dist: requests[socks]
Requires-Dist: aiohttp
Requires-Dist: aiofiles
